hckr/__about__.py
hckr/__init__.py
hckr/__main__.py
hckr/cli/__init__.py
hckr/cli/azure.py
hckr/cli/config.py
hckr/cli/configure.py
hckr/cli/cron.py
hckr/cli/data.py
hckr/cli/db.py
hckr/cli/dt.py
hckr/cli/env.py
hckr/cli/hash.py
hckr/cli/info.py
hckr/cli/net.py
hckr/cli/crypto/__init__.py
hckr/cli/crypto/fernet.py
hckr/cli/k8s/__init__.py
hckr/cli/k8s/context.py
hckr/cli/k8s/namespace.py
hckr/cli/k8s/pod.py
hckr/utils/AzureUtils.py
hckr/utils/CliUtils.py
hckr/utils/CronUtils.py
hckr/utils/CryptoUtils.py
hckr/utils/DataUtils.py
hckr/utils/DbUtils.py
hckr/utils/EnvUtils.py
hckr/utils/FileUtils.py
hckr/utils/HashUtils.py
hckr/utils/MessageUtils.py
hckr/utils/NetUtils.py
hckr/utils/TimeUtils.py
hckr/utils/config/ConfigUtils.py
hckr/utils/config/ConfigureUtils.py
hckr/utils/config/Constants.py
hckr/utils/k8s/K8sUtils.py
hckr/utils/k8s/PodUtils.py
hckr-0.6.0.dist-info/METADATA
hckr-0.6.0.dist-info/WHEEL
hckr-0.6.0.dist-info/entry_points.txt
hckr-0.6.0.dist-info/licenses/LICENSE
hckr-0.6.0.dist-info/RECORD
