Metadata-Version: 2.4
Name: hckr
Version: 0.6.0
Project-URL: Documentation, https://hckr.readthedocs.io
Project-URL: Issues, https://github.com/hckr-cli/hckr/issues
Project-URL: Source, https://github.com/hckr-cli/hckr
Author-email: Ashish Patel <ashishpatel0720@gmail.com>
License-Expression: MIT
License-File: LICENSE
Keywords: cli,dev-tools,hckr
Classifier: Development Status :: 4 - Beta
Classifier: Programming Language :: Python
Classifier: Programming Language :: Python :: 3.8
Classifier: Programming Language :: Python :: 3.9
Classifier: Programming Language :: Python :: 3.10
Classifier: Programming Language :: Python :: 3.11
Classifier: Programming Language :: Python :: 3.12
Classifier: Programming Language :: Python :: Implementation :: CPython
Classifier: Programming Language :: Python :: Implementation :: PyPy
Requires-Python: >=3.8
Requires-Dist: azure-identity
Requires-Dist: azure-mgmt-resource
Requires-Dist: backports-zoneinfo; python_version < '3.9'
Requires-Dist: click
Requires-Dist: click-repl
Requires-Dist: cron-descriptor
Requires-Dist: croniter
Requires-Dist: cryptography
Requires-Dist: faker
Requires-Dist: fastavro
Requires-Dist: kubernetes
Requires-Dist: openpyxl
Requires-Dist: packaging
Requires-Dist: pandas
Requires-Dist: psycopg2-binary
Requires-Dist: pyarrow
Requires-Dist: pymysql
Requires-Dist: requests
Requires-Dist: rich
Requires-Dist: sentry-sdk
Requires-Dist: snowflake-sqlalchemy
Requires-Dist: speedtest-cli
Requires-Dist: sqlalchemy
Requires-Dist: xlrd
Requires-Dist: yaspin
